vcpizza/__init__.py
vcpizza/__main__.py
vcpizza/cli.py
vcpizza/config.py
vcpizza/environment.py
vcpizza/exceptions.py
vcpizza/extensions.py
vcpizza/find.py
vcpizza/generate.py
vcpizza/log.py
vcpizza/main.py
vcpizza/prompt.py
vcpizza/replay.py
vcpizza/repository.py
vcpizza/utils.py
vcpizza/vcs.py
vcpizza-0.1.5.dist-info/METADATA
vcpizza-0.1.5.dist-info/WHEEL
vcpizza-0.1.5.dist-info/entry_points.txt
vcpizza-0.1.5.dist-info/top_level.txt
vcpizza-0.1.5.dist-info/RECORD
