Metadata-Version: 2.1
Name: vcpizza
Version: 0.1.5
Summary: Package to create VCPizza
Author: NguyenVT
Author-email: nguyenvothanh@channelvl.net
Classifier: Programming Language :: Python :: 3
Classifier: License :: OSI Approved :: MIT License
Classifier: Operating System :: OS Independent
Requires-Python: >=3.7
Requires-Dist: binaryornot
Requires-Dist: Jinja2
Requires-Dist: click
Requires-Dist: pyyaml
Requires-Dist: jinja2-time
Requires-Dist: python-slugify
Requires-Dist: requests
